{
  "name": "Human High Contrast",
  "type": "dark",
  "colors": {
    "editor.background": "#000000",
    "editor.foreground": "#FFFFFF",
    "editorLineNumber.foreground": "#666666",
    "editorLineNumber.activeForeground": "#BBBBBB",
    "editorCursor.foreground": "#00FF00",
    "editor.selectionBackground": "#224466",
    "editor.inactiveSelectionBackground": "#1A1A1A80",
    "editor.selectionHighlightBackground": "#22334460",
    "editor.wordHighlightBackground": "#20202080",
    "editor.wordHighlightStrongBackground": "#30303080",
    "editor.findMatchBackground": "#FFFF00",
    "editor.findMatchHighlightBackground": "#AAAA0060",
    "editor.hoverHighlightBackground": "#181818",
    "sideBar.background": "#000000",
    "sideBar.foreground": "#CCCCCC",
    "sideBar.border": "#00000000",
    "activityBar.background": "#000000",
    "activityBar.foreground": "#00FF00",
    "activityBar.inactiveForeground": "#888888",
    "activityBar.border": "#00000000",
    "statusBar.background": "#000000",
    "statusBar.foreground": "#CCCCCC",
    "statusBar.border": "#00000000",
    "panel.background": "#000000",
    "panel.border": "#00000000",
    "tab.activeBackground": "#000000",
    "tab.inactiveBackground": "#000000",
    "tab.border": "#00000000",
    "titleBar.activeBackground": "#000000",
    "titleBar.activeForeground": "#FFFFFF",
    "titleBar.border": "#00000000",
    "list.activeSelectionBackground": "#224466",
    "list.activeSelectionForeground": "#FFFFFF",
    "list.hoverBackground": "#181818",
    "list.inactiveSelectionBackground": "#1A1A1A",
    "list.focusOutline": "#00000000",
    "list.focusAndSelectionOutline": "#00000000",
    "tree.indentGuidesStroke": "#101010",
    "focusBorder": "#00FF0040",
    "contrastBorder": "#00000000",
    "textLink.foreground": "#00DDFF",
    "textLink.activeForeground": "#00FF00",
    "input.background": "#000000",
    "input.border": "#101010",
    "input.foreground": "#FFFFFF",
    "input.placeholderForeground": "#888888",
    "dropdown.background": "#000000",
    "dropdown.border": "#101010",
    "dropdown.foreground": "#FFFFFF",
    "scrollbar.shadow": "#00000000",
    "scrollbarSlider.background": "#88888820",
    "scrollbarSlider.hoverBackground": "#88888840",
    "scrollbarSlider.activeBackground": "#00FF0060",
    "breadcrumb.foreground": "#00CCEE",
    "breadcrumb.background": "#000000",
    "breadcrumb.focusForeground": "#00FF00",
    "breadcrumb.activeSelectionForeground": "#00FF00",
    "terminal.background": "#000000",
    "terminal.foreground": "#FFFFFF",
    "terminal.ansiBlack": "#FFFFFF",
    "terminal.ansiRed": "#FF0000",
    "terminal.ansiGreen": "#00DD00",
    "terminal.ansiYellow": "#FFCC00",
    "terminal.ansiBlue": "#00DDFF",
    "terminal.ansiMagenta": "#EE0000",
    "terminal.ansiCyan": "#00CCEE",
    "terminal.ansiWhite": "#888888",
    "terminal.ansiBrightBlack": "#888888",
    "terminal.ansiBrightRed": "#FF4444",
    "terminal.ansiBrightGreen": "#00DD00",
    "terminal.ansiBrightYellow": "#FFCC00",
    "terminal.ansiBrightBlue": "#00DDFF",
    "terminal.ansiBrightMagenta": "#EE0000",
    "terminal.ansiBrightCyan": "#00DDFF",
    "terminal.ansiBrightWhite": "#FFFFFF",
    "editorBracketHighlight.foreground1": "#FFCC00",
    "editorBracketHighlight.foreground2": "#FF9900",
    "editorBracketHighlight.foreground3": "#FFCC00",
    "editorBracketHighlight.foreground4": "#EE0000",
    "editorBracketHighlight.foreground5": "#FFCC00",
    "editorBracketHighlight.foreground6": "#00FF00",
    "editorBracketHighlight.unexpectedBracket.foreground": "#FF0000",
    "editorError.foreground": "#FF0000",
    "editorWarning.foreground": "#FFCC00",
    "editorInfo.foreground": "#00DDFF",
    "editorHint.foreground": "#00DD00",
    "editorError.background": "#2A000030",
    "editorWarning.background": "#00000030",
    "editorInfo.background": "#00000030",
    "editorGutter.modifiedBackground": "#FFCC00",
    "editorGutter.addedBackground": "#00EE00",
    "editorGutter.deletedBackground": "#FF0000",
    "editorGutter.foldingControlForeground": "#888888",
    "problemsErrorIcon.foreground": "#FF0000",
    "problemsWarningIcon.foreground": "#FFCC00",
    "problemsInfoIcon.foreground": "#00DDFF",
    "gitDecoration.modifiedResourceForeground": "#FFCC00",
    "gitDecoration.addedResourceForeground": "#00EE00",
    "gitDecoration.deletedResourceForeground": "#FF0000",
    "gitDecoration.untrackedResourceForeground": "#00DD00",
    "gitDecoration.conflictingResourceForeground": "#EE0000",
    "gitDecoration.ignoredResourceForeground": "#888888",
    "diffEditor.insertedTextBackground": "#00EE0015",
    "diffEditor.removedTextBackground": "#FF444415",
    "extensionButton.prominentBackground": "#00FF00",
    "extensionButton.prominentForeground": "#000000",
    "extensionButton.prominentHoverBackground": "#00EE00",
    "symbolIcon.classForeground": "#00DDFF",
    "symbolIcon.functionForeground": "#00EE00",
    "symbolIcon.variableForeground": "#FFFFFF",
    "symbolIcon.keywordForeground": "#00FF00"
  },
  "tokenColors": [
    {
      "scope": [
        "keyword",
        "storage.type",
        "storage.modifier"
      ],
      "settings": {
        "foreground": "#00FF00"
      }
    },
    {
      "scope": [
        "entity.name.type",
        "support.type",
        "support.class"
      ],
      "settings": {
        "foreground": "#00DDFF"
      }
    },
    {
      "scope": [
        "entity.name.function",
        "support.function"
      ],
      "settings": {
        "foreground": "#00EE00"
      }
    },
    {
      "scope": [
        "string"
      ],
      "settings": {
        "foreground": "#FFCC00"
      }
    },
    {
      "scope": [
        "constant.numeric"
      ],
      "settings": {
        "foreground": "#FF9900"
      }
    },
    {
      "scope": [
        "comment"
      ],
      "settings": {
        "foreground": "#888888"
      }
    },
    {
      "scope": [
        "keyword.operator"
      ],
      "settings": {
        "foreground": "#00CCEE"
      }
    },
    {
      "scope": [
        "entity.name.tag"
      ],
      "settings": {
        "foreground": "#FFCC00"
      }
    },
    {
      "scope": [
        "entity.other.attribute-name"
      ],
      "settings": {
        "foreground": "#DDAA00"
      }
    },
    {
      "scope": [
        "punctuation.definition.tag"
      ],
      "settings": {
        "foreground": "#CCAA00"
      }
    }
  ],
  "semanticTokenColors": {
    "keyword": "#00FF00",
    "keyword.control": "#00FF00",
    "type": "#00DDFF",
    "type.builtin": "#00DDFF",
    "namespace": "#00DDFF",
    "class.builtin": "#00CCEE",
    "struct.builtin": "#00BBDD",
    "function.builtin": "#00EE00",
    "variable.builtin": "#00CCEE",
    "function": "#00EE00",
    "variable": "#FFFFFF",
    "number": "#FF9900",
    "string": "#FFCC00",
    "string.escape": "#FF0000",
    "operator": "#00CCEE",
    "comment": "#888888",
    "property": "#FFFFFF",
    "parameter": "#FFFFFF"
  }
}